{
    "company": {
        "name": "Golden Gate Manor, Inc.",
        "short_name": "Golden Gate Manor",
        "phone_number_nemt": "719-544-3231",
        "phone_number_dispatch": "719-543-2525",
        "phone_number_assisted_living": "719-696-8032",
        "phone_number_nemt_format": "(719) 544-3231",
        "phone_number_dispatch_format": "(719) 543-2525",
        "phone_number_assisted_living_format": "(719) 696-8032",
        "address_admin": "612 S. Union Ave.",
        "address_transportation": "648 S. Union Ave.",
        "city": "Pueblo",
        "state": "Colorado",
        "zipcode": "81004",
        "reservation_hours": "8:00AM-4:00PM Monday to Friday",
        "favicon": "/images/favicon.ico",
        "logo_src": "/images/Logo.png",
        "logo_alt": "Logo reading: Golden Gate Manor, Inc.",
        "home_href": "/",
        "slogan": "PEOPLE WHO VALUE THEIR QUALITY OF LIFE CAN DEPEND ON US",
        "mission_statement": "To improve The Quality of Life Each and Every Day.",
        "social": {
            "facebook": {
                "logo_src": "/images/facebook.svg",
                "href": "https://www.facebook.com/GoldenGateManor/"
            }
        }
    },
    "links": {
        "home": {
            "title": "Home",
            "href": "/"
        },
        "assisted_living": {
            "title": "Assisted Living",
            "href": "/assisted-living"
        },
        "non_medical": {
            "title": "Non-Medical Transportation",
            "href": "/non-medical-transportation"
        },
        "nemt": {
            "title": "NEMT Transportation",
            "href": "/nemt"
        },
        "medical_supply": {
            "title": "Medical Supplies",
            "href": "https://www.goldengatemedicalsupply.com"
        },
        "about_us": {
            "title": "About Us",
            "href": "/about-us",
            "sublinks": {
                "about_us": {
                    "title": "About Us",
                    "href": "/about-us"
                },
                "blog": {
                    "title": "Blog",
                    "href": "/blogs"
                },
                "location": {
                    "title": "Location",
                    "href": "/about-us/location"
                },
                "community": {
                    "title": "Community",
                    "href": "/about-us/community"
                }
            }
        },
        "contact_us": {
            "title": "Contact Us",
            "href": "/contact-us",
            "sublinks": {
                "contact_us": {
                    "title": "Contact Us",
                    "href": "/contact-us"
                },
                "schedule_a_ride": {
                    "title": "Schedule A Ride",
                    "href": "/contact-us/schedule-a-ride"
                }
            }
        }
    },
    "footer_links": {
        "privacy_policy": {
            "title": "Privacy Policy",
            "href": "/privacy-policy"
        },
        "accessibility": {
            "title": "Accessibility",
            "href": "/accessibility"
        },
        "site_map": {
            "title": "Site Map",
            "href": "/site-map"
        }
    }
}